ckanext/__init__.py
ckanext/js_tweaks/__init__.py
ckanext/js_tweaks/helpers.py
ckanext/js_tweaks/plugin.py
ckanext/js_tweaks/assets/webassets.yml
ckanext/js_tweaks/assets/css/js-tweaks.css
ckanext/js_tweaks/assets/css/base/OverlayScrollbars.min.css
ckanext/js_tweaks/assets/js/tweaks-scrollbars.js
ckanext/js_tweaks/assets/js/tweaks-search-facet.js
ckanext/js_tweaks/assets/js/tweaks-select.js
ckanext/js_tweaks/assets/js/tweaks-show-more.js
ckanext/js_tweaks/assets/js/tweaks-toggle-class.js
ckanext/js_tweaks/assets/js/tweaks-toogle-tooltip.js
ckanext/js_tweaks/assets/js/base/OverlayScrollbars.min.js
ckanext/js_tweaks/templates/page.html
ckanext/js_tweaks/templates/macros/accordion.html
ckanext/js_tweaks/templates/macros/lang_select.html
ckanext/js_tweaks/templates/macros/sort_select.html
ckanext/js_tweaks/tests/__init__.py
ckanext/js_tweaks/tests/test_plugin.py
ckanext/js_tweaks/theme/global.less
ckanext/js_tweaks/theme/js-tweaks.less
ckanext/js_tweaks/theme/mixin.less
ckanext/js_tweaks/theme/mixins.less
ckanext/js_tweaks/theme/select.less
ckanext/js_tweaks/theme/tooltip.less
ckanext/js_tweaks/theme/variables.less
ckanext_js_tweaks-0.0.31.dist-info/LICENSE
ckanext_js_tweaks-0.0.31.dist-info/METADATA
ckanext_js_tweaks-0.0.31.dist-info/WHEEL
ckanext_js_tweaks-0.0.31.dist-info/entry_points.txt
ckanext_js_tweaks-0.0.31.dist-info/top_level.txt
ckanext_js_tweaks-0.0.31.dist-info/RECORD
