Metadata-Version: 2.1
Name: ckanext-js-tweaks
Version: 0.0.31
Summary: JS scripts to improve UI expirience
Author-email: DataShades <datashades@linkdigital.com.au>, Oleksandr Cherniavskyi <mutantsan@gmail.com>
Maintainer-email: DataShades <datashades@linkdigital.com.au>
License: AGPL
Project-URL: Homepage, https://github.com/DataShades/ckanext-js-tweaks
Keywords: CKAN,scheming,schema
Classifier: Development Status :: 4 - Beta
Classifier: License :: OSI Approved :: GNU Affero General Public License v3 or later (AGPLv3+)
Classifier: Programming Language :: Python :: 3.8
Requires-Python: >=3.8
License-File: LICENSE
Requires-Dist: ckanext-scheming
Requires-Dist: typing-extensions
